{"posting_id":"10025148","locale":"ka","type":"იყიდება","property_type":"ბინა","date":"2015-01-04","additional_info":"ავეჯი, ტელეფონი, ინტერნეტი, საკაბელო TV, გათბობა: ცენტრალური, ცხ წყალი: გაზი \n 4 დიდი ოთახი, საკეთებელი არაფერი არ არის, გათბობა იატაკშიც არის დამონტაჟებული, ძალიან კარგი გემოვნებით გაკეთებული ევრორემონტი, მანსარდის დაშენების პერსპერქტივით, ბუხარი ფუნქციონირებს, 2 აივანი, ძალიან სუფთა და კომფორტული ბინააა, შესაძლებელია გაყიდვა ნაწილობრივ ავეჯითაც. 591 19 83 19 ზაზა","details":{"daily_rent":null,"for_rent":null,"for_sale":"65000 $ / 590.91 $ m²","for_lease":null,"est_lease_price":null,"rent_price":null,"rent_price_currency":null,"rent_price_sq_meter":null,"rent_price_dollars":null,"rent_price_sq_meter_dollars":null,"rent_price_exchange_rate_to_dollars":null,"sale_price":"65000","sale_price_currency":"$","sale_price_sq_meter":"590.91","sale_price_dollars":65000.0,"sale_price_sq_meter_dollars":590.91,"sale_price_exchange_rate_to_dollars":1.0,"space":"115","space_measurement":"კვ.მ.","land":null,"land_measurement":null,"renovation":"ევრორემონტი","view":"მთელი ქალაქი","project":"ქალაქური","condition":null,"function":null,"address":"ქუთაისი","address_city":"ქუთაისი","address_area":null,"address_district":null,"address_street":null,"address_number":null,"phone":"571828220; 595131321;","cadastral":null},"specs":{"all_floors":"4","floor":"4","rooms":"4","bedrooms":"2","conference_room":null,"suites":null,"wc":"2","bathroom":null,"shower":"1","fireplace":"1","air_conditioner":"1","balcony":"2","veranda":null,"loft":null,"bodrum":null,"mansard":null,"parking":null,"garage":null,"dist_from_tbilisi":null,"dist_from_cent_street":null,"box":null,"buildings":null,"administration_building":null,"workroom":null,"stockroom":null,"coefficient_k1":null,"coefficient_k2":null}}