{"posting_id":"6335766","locale":"en","type":"for sale","property_type":"private house","date":"2014-04-10","additional_info":"Swimming pool, Storeroom, Wardrobe, Alarm System, Window guards","details":{"daily_rent":null,"for_rent":null,"for_sale":"165000 $ / 330.00 $ m²","for_lease":null,"est_lease_price":null,"rent_price":null,"rent_price_currency":null,"rent_price_exchange_rate":1,"rent_price_sq_meter":null,"sale_price":"165000","sale_price_currency":"$","sale_price_exchange_rate":1,"sale_price_sq_meter":"330.00","space":"500","space_measurement":"sq.m.","land":"735","land_measurement":"sq.m.","renovation":"White frame","view":"City","project":null,"condition":"New building","function":null,"address":"Mtskheta","address_city":"Mtskheta","address_area":null,"address_district":null,"address_street":null,"address_number":null,"phone":"2471020; 595925020;","cadastral":null},"specs":{"all_floors":"4","floor":null,"rooms":"7","bedrooms":"6","conference_room":null,"suites":null,"wc":"4","bathroom":null,"shower":null,"fireplace":"2","air_conditioner":null,"balcony":"4","veranda":"20","loft":null,"bodrum":null,"mansard":null,"parking":null,"garage":"2","dist_from_tbilisi":null,"dist_from_cent_street":null,"box":null,"buildings":null,"administration_building":null,"workroom":null,"stockroom":null,"coefficient_k1":null,"coefficient_k2":null}}