{"posting_id":"10019193","locale":"en","type":"for rent","property_type":"commercial space","date":"2014-03-18","additional_info":"Working, Inventory, Heating system: electricity","details":{"daily_rent":null,"for_rent":"400 GEL / 13.33 GEL m²","for_sale":null,"for_lease":null,"est_lease_price":null,"rent_price":"400","rent_price_currency":"GEL","rent_price_exchange_rate":1,"rent_price_sq_meter":"13.33","sale_price":null,"sale_price_currency":null,"sale_price_exchange_rate":1,"sale_price_sq_meter":null,"space":"30","space_measurement":"sq.m.","land":null,"land_measurement":null,"renovation":"Renovated","view":null,"project":null,"condition":"New building","function":"Shop","address":"Tbilisi, Gldani-Nadzaladevi,  Gldani, Microdistrict VI","address_city":"Tbilisi","address_area":"Gldani-Nadzaladevi","address_district":"Gldani","address_street":"Microdistrict VI","address_number":null,"phone":"790228165; 599228165;","cadastral":null},"specs":{"all_floors":"2","floor":"1","rooms":"1","bedrooms":null,"conference_room":null,"suites":null,"wc":"1","bathroom":null,"shower":null,"fireplace":null,"air_conditioner":"1","balcony":null,"veranda":null,"loft":null,"bodrum":null,"mansard":null,"parking":null,"garage":null,"dist_from_tbilisi":null,"dist_from_cent_street":null,"box":null,"buildings":null,"administration_building":null,"workroom":null,"stockroom":null,"coefficient_k1":null,"coefficient_k2":null}}