{"posting_id":"10022023","locale":"ka","type":"ქირავდება","property_type":"საკუთარი სახლი","date":"2014-04-25","additional_info":"სათავსო, ავეჯი, ტექნიკა, ინტერნეტი, ტელეფონი, საკაბელო TV, სატელიტი, გათბობა: გაზი, ცხ წყალი: გაზი, დენი \n ქირავდება ახალი აშენებული 3 სართულიანი სახლი წყნეთში, ფიჭვნარში. დიდი ეზო გარე სამზარეულოთი, ყველა კომუნიკაციით, საერთო ფართი 360 კვ.მ, ეზოს ფართი 900 კვ.მ, ავეჯით, ტექნიკით, 5 საძინებლით, 3 სველი წერტილით, 3 მისაღები ოთახით, დიდი ვერანდებით, ა/პარკინგით 5 მანქანაზე. (შესაძლოა გაქირავება წლიურადაც და სეზონზეც)","details":{"daily_rent":null,"for_rent":"7000 $ / 19.44 $ m²","for_sale":null,"for_lease":null,"est_lease_price":null,"rent_price":"7000","rent_price_currency":"$","rent_price_sq_meter":"19.44","rent_price_dollars":7000.0,"rent_price_sq_meter_dollars":19.44,"rent_price_exchange_rate_to_dollars":1.0,"sale_price":null,"sale_price_currency":null,"sale_price_sq_meter":null,"sale_price_dollars":null,"sale_price_sq_meter_dollars":null,"sale_price_exchange_rate_to_dollars":null,"space":"360","space_measurement":"კვ.მ.","land":"900","land_measurement":"კვ.მ.","renovation":"გარემონტებული","view":"ეზო","project":null,"condition":"ახალი აშენებული","function":null,"address":"თბილისი, დიდგორი, წყნეთი","address_city":"თბილისი","address_area":"დიდგორი","address_district":"წყნეთი","address_street":null,"address_number":null,"phone":"2471020; 595925020;","cadastral":null},"specs":{"all_floors":"3","floor":null,"rooms":"8","bedrooms":"5","conference_room":null,"suites":null,"wc":"3","bathroom":null,"shower":null,"fireplace":"4","air_conditioner":null,"balcony":"3","veranda":null,"loft":null,"bodrum":null,"mansard":null,"parking":"3","garage":"2","dist_from_tbilisi":null,"dist_from_cent_street":null,"box":null,"buildings":null,"administration_building":null,"workroom":null,"stockroom":null,"coefficient_k1":null,"coefficient_k2":null}}