{"posting_id":"10059063","locale":"ka","type":"იყიდება","property_type":"ბინა","date":"2015-10-26","additional_info":"ტელეფონი, ინტერნეტი, კუთხის, ლიფტი, გათბობა: გაზი, დენი, ცხ წყალი: გაზი, დენი \n ეკოლოგიურად სუფთა ადგილზე     კუთხის ნათელი ბინა იზოლირებული სამზარეულო","details":{"daily_rent":null,"for_rent":null,"for_sale":"65000 $ / 755.81 $ m²","for_lease":null,"est_lease_price":null,"rent_price":null,"rent_price_currency":null,"rent_price_sq_meter":null,"rent_price_dollars":null,"rent_price_sq_meter_dollars":null,"rent_price_exchange_rate_to_dollars":null,"sale_price":"65000","sale_price_currency":"$","sale_price_sq_meter":"755.81","sale_price_dollars":65000.0,"sale_price_sq_meter_dollars":755.81,"sale_price_exchange_rate_to_dollars":1.0,"space":"86","space_measurement":"კვ.მ.","land":null,"land_measurement":null,"renovation":"სარემონტო","view":null,"project":"ყავლაშვილის","condition":"ძველი აშენებული","function":null,"address":"თბილისი, საბურთალო, საბურთალო, ფანასკერტელ-ციციშვილის ქ.","address_city":"თბილისი","address_area":"საბურთალო","address_district":"საბურთალო","address_street":"ფანასკერტელ-ციციშვილის ქ.","address_number":null,"phone":"2471020; 595925030;","cadastral":null},"specs":{"all_floors":"16","floor":"3","rooms":"3","bedrooms":"2","conference_room":null,"suites":null,"wc":"2","bathroom":"1","shower":null,"fireplace":null,"air_conditioner":null,"balcony":null,"veranda":null,"loft":null,"bodrum":null,"mansard":null,"parking":null,"garage":null,"dist_from_tbilisi":null,"dist_from_cent_street":null,"box":null,"buildings":null,"administration_building":null,"workroom":null,"stockroom":null,"coefficient_k1":null,"coefficient_k2":null}}