{"posting_id":"10008931","locale":"en","type":"for sale","property_type":"land","date":"2014-06-24","additional_info":"on central road, Fenced, Fruits, Communications: electricity, gas, Water, Сanalization \n gvesaciroeba investori gvak 6 sartuliani mraval sacxovrebeli saxlis proekti","details":{"daily_rent":null,"for_rent":null,"for_sale":"420000 $ / 600.00 $ m²","for_lease":null,"est_lease_price":null,"rent_price":null,"rent_price_currency":null,"rent_price_sq_meter":null,"rent_price_dollars":null,"rent_price_sq_meter_dollars":null,"rent_price_exchange_rate_to_dollars":null,"sale_price":"420000","sale_price_currency":"$","sale_price_sq_meter":"600.00","sale_price_dollars":420000.0,"sale_price_sq_meter_dollars":600.0,"sale_price_exchange_rate_to_dollars":1.0,"space":"700","space_measurement":"sq.m.","land":"600","land_measurement":"sq.m.","renovation":null,"view":null,"project":null,"condition":null,"function":"Non Agricultural","address":"Tbilisi, Old Tbilisi,  Vera, R. Djafaridze st.","address_city":"Tbilisi","address_area":"Old Tbilisi","address_district":"Vera","address_street":"R. Djafaridze st.","address_number":null,"phone":"2471020; 595925020;","cadastral":null},"specs":{"all_floors":null,"floor":null,"rooms":null,"bedrooms":null,"conference_room":null,"suites":null,"wc":null,"bathroom":null,"shower":null,"fireplace":null,"air_conditioner":null,"balcony":null,"veranda":null,"loft":null,"bodrum":null,"mansard":null,"parking":null,"garage":null,"dist_from_tbilisi":null,"dist_from_cent_street":null,"box":null,"buildings":"3","administration_building":null,"workroom":null,"stockroom":null,"coefficient_k1":"2.4","coefficient_k2":"1.8"}}