{"posting_id":"10061120","locale":"ka","type":"იყიდება","property_type":"საკუთარი სახლი","date":"2015-08-26","additional_info":"ჯაკუზი, სათავსო, ინტერნეტი, საკაბელო TV, სატელიტი, გისოსები, გათბობა: ცენტრალური, ცხ წყალი: გაზი, დენი \n დელისის ქუჩაზე, ნუცუბიძის ქუჩის ზემოთ, ეკოლოგიურად სუფთა გარემოში, იყიდება კერძო სახლის პირველი სართული თავისი ეზოთი. საცხოვრებელი ფართი 135 მ. კვ., კაპიტალური სარდაფი 12 მ.კვ., ეზო 75 მ.კვ. 1 ზალა, 1 დამხმარე ოთახი, 3 საძინებელი, 2 სველი წერტილი. რემონტი ახალი, ელექტროობა და გაყვანილობა მაღალი ხარისხის ევროპული მასალების. ცენტრალური გათბობა. სახლამდე მიდის ასფალტირებული ახალი გზა თ. ნადარეიშვილის ქუჩიდან, ასევე დელისის ქუჩიდან","details":{"daily_rent":null,"for_rent":null,"for_sale":"155000 $ / 1148.15 $ m²","for_lease":null,"est_lease_price":null,"rent_price":null,"rent_price_currency":null,"rent_price_sq_meter":null,"rent_price_dollars":null,"rent_price_sq_meter_dollars":null,"rent_price_exchange_rate_to_dollars":null,"sale_price":"155000","sale_price_currency":"$","sale_price_sq_meter":"1148.15","sale_price_dollars":155000.0,"sale_price_sq_meter_dollars":1148.15,"sale_price_exchange_rate_to_dollars":1.0,"space":"135","space_measurement":"კვ.მ.","land":"75","land_measurement":"კვ.მ.","renovation":"ახალი გარემონტებული","view":"ბაღი","project":null,"condition":"ახალი აშენებული","function":null,"address":"თბილისი, საბურთალო, საბურთალო, დელისის ქ.","address_city":"თბილისი","address_area":"საბურთალო","address_district":"საბურთალო","address_street":"დელისის ქ.","address_number":null,"phone":"2471020; 595925020;","cadastral":null},"specs":{"all_floors":"1","floor":null,"rooms":"5","bedrooms":"3","conference_room":null,"suites":null,"wc":"2","bathroom":"1","shower":null,"fireplace":"1","air_conditioner":null,"balcony":"1","veranda":null,"loft":null,"bodrum":"12","mansard":null,"parking":null,"garage":null,"dist_from_tbilisi":null,"dist_from_cent_street":null,"box":null,"buildings":null,"administration_building":null,"workroom":null,"stockroom":null,"coefficient_k1":null,"coefficient_k2":null}}