{"posting_id":"10066672","locale":"ka","type":"იყიდება","property_type":"საკუთარი სახლი","date":"2015-11-05","additional_info":"გათბობა: გაზი, დენი \n ","details":{"daily_rent":null,"for_rent":null,"for_sale":"200000 $ / 666.67 $ m²","for_lease":null,"est_lease_price":null,"rent_price":null,"rent_price_currency":null,"rent_price_sq_meter":null,"rent_price_dollars":null,"rent_price_sq_meter_dollars":null,"rent_price_exchange_rate_to_dollars":null,"sale_price":"200000","sale_price_currency":"$","sale_price_sq_meter":"666.67","sale_price_dollars":200000.0,"sale_price_sq_meter_dollars":666.67,"sale_price_exchange_rate_to_dollars":1.0,"space":"300","space_measurement":"კვ.მ.","land":"80","land_measurement":"კვ.მ.","renovation":"მიმდინარე რემონტი","view":null,"project":null,"condition":null,"function":null,"address":"თბილისი, ისანი, ნავთლუღი, მალხაზის ქ.","address_city":"თბილისი","address_area":"ისანი","address_district":"ნავთლუღი","address_street":"მალხაზის ქ.","address_number":null,"phone":"2471020; 599194070;","cadastral":null},"specs":{"all_floors":"4","floor":null,"rooms":"8","bedrooms":"4","conference_room":null,"suites":null,"wc":"5","bathroom":null,"shower":null,"fireplace":"1","air_conditioner":null,"balcony":"2","veranda":null,"loft":null,"bodrum":"77","mansard":"60","parking":"1","garage":null,"dist_from_tbilisi":null,"dist_from_cent_street":null,"box":null,"buildings":null,"administration_building":null,"workroom":null,"stockroom":null,"coefficient_k1":null,"coefficient_k2":null}}