{"posting_id":"3356457","locale":"ka","type":"ქირავდება","property_type":"საკუთარი სახლი","date":"2014-04-10","additional_info":"ინტერნეტი, ტელეფონი, საკაბელო TV, გათბობა: გაზი, ცხ წყალი: გაზი \n ცენტრალური გათბობით.","details":{"daily_rent":null,"for_rent":"700 $ / 10.77 $ m²","for_sale":null,"for_lease":null,"rent_price":"700","rent_price_currency":"$","rent_price_exchange_rate":1,"rent_price_sq_meter":"10.77","sale_price":null,"sale_price_currency":null,"sale_price_exchange_rate":1,"sale_price_sq_meter":null,"space":"65","space_measurement":"კვ.მ.","land":"100","land_measurement":"კვ.მ.","renovation":"ახალი გარემონტებული","view":null,"project":null,"condition":null,"function":null,"address":"თბილისი, ძველი თბილისი, მთაწმინდა, რიწის ქ.","address_city":"თბილისი","address_area":"ძველი თბილისი","address_district":"მთაწმინდა","address_street":"რიწის ქ.","address_number":null,"phone":"2471020; 595925020;","cadastral":null},"specs":{"all_floors":"1","floor":null,"rooms":"3","bedrooms":"2","conference_room":null,"wc":"2","bathroom":null,"shower":null,"fireplace":null,"air_conditioner":"2","balcony":null,"veranda":"30","loft":null,"bodrum":null,"mansard":null,"parking":null,"garage":null,"dist_from_tbilisi":null,"dist_from_cent_street":null,"box":null,"buildings":null,"administration_building":null,"workroom":null,"stockroom":null,"coefficient_k1":null,"coefficient_k2":null}}