{"posting_id":"9143330","locale":"ka","type":"იყიდება","property_type":"საკუთარი სახლი","date":"2014-08-20","additional_info":"აუზი, საგარდერობო \n ავდარაანთ კარში ვილა  ხეხილიანი ეზოთ, 10 დიდი კაკლის ხე, ეზოში ცალკე ბასეინით, ჭაბურღილით,  3 მეტრიანი შემოღობილი გალავნით. პანორამული ხედებით.","details":{"daily_rent":null,"for_rent":null,"for_sale":"155000 $ / 129.17 $ m²","for_lease":null,"est_lease_price":null,"rent_price":null,"rent_price_currency":null,"rent_price_sq_meter":null,"rent_price_dollars":null,"rent_price_sq_meter_dollars":null,"rent_price_exchange_rate_to_dollars":null,"sale_price":"155000","sale_price_currency":"$","sale_price_sq_meter":"129.17","sale_price_dollars":155000.0,"sale_price_sq_meter_dollars":129.17,"sale_price_exchange_rate_to_dollars":1.0,"space":"1200","space_measurement":"კვ.მ.","land":"3000","land_measurement":"კვ.მ.","renovation":"შავი კარკასი","view":"ლამაზი","project":null,"condition":null,"function":null,"address":"საგურამო","address_city":"საგურამო","address_area":null,"address_district":null,"address_street":null,"address_number":null,"phone":"2471020; 595925020;","cadastral":null},"specs":{"all_floors":"4","floor":null,"rooms":"21","bedrooms":null,"conference_room":null,"suites":null,"wc":"4","bathroom":null,"shower":null,"fireplace":"4","air_conditioner":null,"balcony":"20","veranda":"100","loft":null,"bodrum":null,"mansard":"300","parking":null,"garage":null,"dist_from_tbilisi":null,"dist_from_cent_street":null,"box":null,"buildings":null,"administration_building":null,"workroom":null,"stockroom":null,"coefficient_k1":null,"coefficient_k2":null}}