{"posting_id":"10027994","locale":"ka","type":"დღიური გაქ.","property_type":"ბინა","date":"2014-07-28","additional_info":"სათავსო, ავეჯი, ტექნიკა, ინტერკომი, ტელეფონი, ინტერნეტი, სატელიტი, ცხ წყალი: დენი \n შესაძლებელია გაქირავება სულადობით(ლოგინი - 25ლარი)\r\nყურადღება: 3 დღეზე ნაკლებად არ ქირავდება. 591715154","details":{"daily_rent":"100 $ / 0.96 $ m²","for_rent":null,"for_sale":null,"for_lease":null,"est_lease_price":null,"rent_price":"100","rent_price_currency":"$","rent_price_sq_meter":"0.96","rent_price_dollars":100.0,"rent_price_sq_meter_dollars":0.96,"rent_price_exchange_rate_to_dollars":1.0,"sale_price":null,"sale_price_currency":null,"sale_price_sq_meter":null,"sale_price_dollars":null,"sale_price_sq_meter_dollars":null,"sale_price_exchange_rate_to_dollars":null,"space":"104","space_measurement":"კვ.მ.","land":null,"land_measurement":null,"renovation":"ახალი გარემონტებული","view":"ზღვა","project":"არასტანდარტული","condition":"ახალი აშენებული","function":null,"address":"ბათუმი","address_city":"ბათუმი","address_area":null,"address_district":null,"address_street":null,"address_number":null,"phone":"2471020; 595925020;","cadastral":null},"specs":{"all_floors":"6","floor":"5","rooms":"5","bedrooms":"3","conference_room":null,"suites":null,"wc":"2","bathroom":null,"shower":"1","fireplace":null,"air_conditioner":null,"balcony":"1","veranda":null,"loft":null,"bodrum":null,"mansard":null,"parking":null,"garage":null,"dist_from_tbilisi":null,"dist_from_cent_street":null,"box":null,"buildings":null,"administration_building":null,"workroom":null,"stockroom":null,"coefficient_k1":null,"coefficient_k2":null}}