{"posting_id":"10069150","locale":"ka","type":"გირავდება","property_type":"ბინა","date":"2015-12-05","additional_info":"ინტერნეტი, საკაბელო TV, გათბობა: გაზი, ცხ წყალი: გაზი \n იტალიურ ეზოში  1,5 ოთახიანი ბინა (სუფთა მდგომარეობაში) ს.ფ. 40 კვ.მ ( H=4.20m) სამზარეულო და აბაზანა-ტუალეტი ბინიდან ერთ მეტრშია.","details":{"daily_rent":null,"for_rent":null,"for_sale":null,"for_lease":"12000 $ / 300.00 $ m²","est_lease_price":null,"rent_price":null,"rent_price_currency":null,"rent_price_sq_meter":null,"rent_price_dollars":null,"rent_price_sq_meter_dollars":null,"rent_price_exchange_rate_to_dollars":null,"sale_price":"12000","sale_price_currency":"$","sale_price_sq_meter":"300.00","sale_price_dollars":12000.0,"sale_price_sq_meter_dollars":300.0,"sale_price_exchange_rate_to_dollars":1.0,"space":"40","space_measurement":"კვ.მ.","land":null,"land_measurement":null,"renovation":"ძველი გარემონტებული","view":null,"project":null,"condition":"ძველი აშენებული","function":null,"address":"თბილისი, ჩუღურეთი, ჩუღურეთი, აღმაშენებლის გამზ., N 53","address_city":"თბილისი","address_area":"ჩუღურეთი","address_district":"ჩუღურეთი","address_street":"აღმაშენებლის გამზ.","address_number":"N 53","phone":"599484706;","cadastral":null},"specs":{"all_floors":"3","floor":"1","rooms":"1.5","bedrooms":"1","conference_room":null,"suites":null,"wc":"1","bathroom":null,"shower":null,"fireplace":null,"air_conditioner":null,"balcony":null,"veranda":null,"loft":null,"bodrum":null,"mansard":null,"parking":null,"garage":null,"dist_from_tbilisi":null,"dist_from_cent_street":null,"box":null,"buildings":null,"administration_building":null,"workroom":null,"stockroom":null,"coefficient_k1":null,"coefficient_k2":null}}