{"posting_id":"3345619","locale":"ka","type":"იყიდება","property_type":"ბინა","date":"2015-04-30","additional_info":"სათავსო, საგარდერობო, ტელეფონი, ინტერნეტი, საკაბელო TV, კუთხის, ლიფტი, გათბობა: გაზი, დენი, ცხ წყალი: დენი \n 14 სართულიანის მე-6 სართული, კუთხის ბინა ზედ რობაქიძის გამძირზე, მშვიდი და ლამაზი ხედებით. სამივე მხარე ამოშენებული აივნით.","details":{"daily_rent":null,"for_rent":null,"for_sale":"80000 $ / 800.00 $ m²","for_lease":null,"est_lease_price":null,"rent_price":null,"rent_price_currency":null,"rent_price_sq_meter":null,"rent_price_dollars":null,"rent_price_sq_meter_dollars":null,"rent_price_exchange_rate_to_dollars":null,"sale_price":"80000","sale_price_currency":"$","sale_price_sq_meter":"800.00","sale_price_dollars":80000.0,"sale_price_sq_meter_dollars":800.0,"sale_price_exchange_rate_to_dollars":1.0,"space":"100","space_measurement":"კვ.მ.","land":null,"land_measurement":null,"renovation":"გარემონტებული","view":"ლამაზი","project":"თუხარელის","condition":null,"function":null,"address":"თბილისი, დიდუბე, დიღმის მასივი, გრ. რობაქიძის გამზ., კვარტალი 3","address_city":"თბილისი","address_area":"დიდუბე","address_district":"დიღმის მასივი","address_street":"გრ. რობაქიძის გამზ.","address_number":"კვარტალი 3","phone":"2471020; 595925020;","cadastral":null},"specs":{"all_floors":"14","floor":"6","rooms":"4","bedrooms":"2","conference_room":null,"suites":null,"wc":"2","bathroom":null,"shower":null,"fireplace":null,"air_conditioner":"1","balcony":null,"veranda":null,"loft":null,"bodrum":"9","mansard":null,"parking":null,"garage":null,"dist_from_tbilisi":null,"dist_from_cent_street":null,"box":null,"buildings":null,"administration_building":null,"workroom":null,"stockroom":null,"coefficient_k1":null,"coefficient_k2":null}}