{"posting_id":"3847004","locale":"en","type":"for sale","property_type":"apartment","date":"2014-03-27","additional_info":"Telephone, Elevator","details":{"daily_rent":null,"for_rent":null,"for_sale":"135000 $ / 900.00 $ m²","for_lease":null,"est_lease_price":null,"rent_price":null,"rent_price_currency":null,"rent_price_exchange_rate":1,"rent_price_sq_meter":null,"sale_price":"135000","sale_price_currency":"$","sale_price_exchange_rate":1,"sale_price_sq_meter":"900.00","space":"150","space_measurement":"sq.m.","land":null,"land_measurement":null,"renovation":"Out of fix","view":"nice","project":null,"condition":null,"function":null,"address":"Tbilisi, Vake-Saburtalo,  Vake, Kekelidze st.","address_city":"Tbilisi","address_area":"Vake-Saburtalo","address_district":"Vake","address_street":"Kekelidze st.","address_number":null,"phone":"2471020; 595925030;","cadastral":null},"specs":{"all_floors":"9","floor":"8","rooms":"4","bedrooms":"3","conference_room":null,"suites":null,"wc":null,"bathroom":null,"shower":null,"fireplace":null,"air_conditioner":null,"balcony":"2","veranda":null,"loft":null,"bodrum":null,"mansard":null,"parking":null,"garage":null,"dist_from_tbilisi":null,"dist_from_cent_street":null,"box":null,"buildings":null,"administration_building":null,"workroom":null,"stockroom":null,"coefficient_k1":null,"coefficient_k2":null}}