{"posting_id":"10059968","locale":"ka","type":"იყიდება","property_type":"საკუთარი სახლი","date":"2015-08-07","additional_info":"სასწრაფოდ! იყიდება 3 სართულიანი სახლი დიდი მანსარდით გორის რ-ნ სოფელ ატენში (დასაწყისში, ყოფილ ფურნესთან) გზის პირას, ეზოთი, ხეხილის ბაღით, დიდი აივნებით. ორმაგი ბლოკის კედლებით, სახურავი - ფიგურებიანი ცინკით. რკინის ალაყაფით, ყველა ფანჯარასა და კარებზე რკინის გისოსებით.","details":{"daily_rent":null,"for_rent":null,"for_sale":"17500 $ / 23.58 $ m²","for_lease":null,"est_lease_price":null,"rent_price":null,"rent_price_currency":null,"rent_price_sq_meter":null,"rent_price_dollars":null,"rent_price_sq_meter_dollars":null,"rent_price_exchange_rate_to_dollars":null,"sale_price":"17500","sale_price_currency":"$","sale_price_sq_meter":"23.58","sale_price_dollars":17500.0,"sale_price_sq_meter_dollars":23.58,"sale_price_exchange_rate_to_dollars":1.0,"space":"742","space_measurement":"კვ.მ.","land":null,"land_measurement":null,"renovation":null,"view":null,"project":null,"condition":null,"function":null,"address":"გორი","address_city":"გორი","address_area":null,"address_district":null,"address_street":null,"address_number":null,"phone":"555590002;","cadastral":null},"specs":{"all_floors":"3","floor":null,"rooms":"6","bedrooms":null,"conference_room":null,"suites":null,"wc":"1","bathroom":null,"shower":null,"fireplace":null,"air_conditioner":null,"balcony":null,"veranda":null,"loft":null,"bodrum":null,"mansard":null,"parking":null,"garage":null,"dist_from_tbilisi":null,"dist_from_cent_street":null,"box":null,"buildings":null,"administration_building":null,"workroom":null,"stockroom":null,"coefficient_k1":null,"coefficient_k2":null}}