{"posting_id":"10006908","locale":"ka","type":"იყიდება","property_type":"ბინა","date":"2015-06-06","additional_info":"სათავსო, საგარდერობო, ტექნიკა, ტელეფონი, ინტერნეტი, საკაბელო TV, დაცვა, სიგნალიზაცია, ლიფტი, გათბობა: ცენტრალური, ცხ წყალი: გაზი, დენი \n იყიდება 5 ოთახიანი პენტჰაუსის ტიპის ბინა ვაკეში, კორპუს გააჩნია 2 ლიფტი, 24 საათიანი დაცვა, სადარბაზო მოპირკეთებულია, კორპუს გააჩნია დაცული ღია ავტოსადგომი.\r\n საერთო ფართი 300 კვ.მ,  ევრორემონტით, 3 საძინებლით, მისაღებით, სასადილო ოთახით, იზოლირებული სამზარეულოთი, დამხმარე (სამრეცხაო) ოთახით, 2 საგარდერობოთი, 3 სველი წერტილით, დიდი 34 კვ.მ–ანი ვერანდით, ცენტრალური გათბობით, ცხელი წყლით, ტელეფონით, ინტერნეტით, ჩაშენებული ავეჯით და ტექნიკით.","details":{"daily_rent":null,"for_rent":null,"for_sale":"470000 $ / 1516.13 $ m²","for_lease":null,"est_lease_price":null,"rent_price":null,"rent_price_currency":null,"rent_price_sq_meter":null,"rent_price_dollars":null,"rent_price_sq_meter_dollars":null,"rent_price_exchange_rate_to_dollars":null,"sale_price":"470000","sale_price_currency":"$","sale_price_sq_meter":"1516.13","sale_price_dollars":470000.0,"sale_price_sq_meter_dollars":1516.13,"sale_price_exchange_rate_to_dollars":1.0,"space":"300","space_measurement":"კვ.მ.","land":null,"land_measurement":null,"renovation":"ევრორემონტი","view":"ლამაზი","project":"არასტანდარტული","condition":"ახალი აშენებული","function":null,"address":"თბილისი, ვაკე, ვაკე, ი. ჭავჭავაძის გამზ.","address_city":"თბილისი","address_area":"ვაკე","address_district":"ვაკე","address_street":"ი. ჭავჭავაძის გამზ.","address_number":null,"phone":"2471020; 595925010;","cadastral":null},"specs":{"all_floors":"14","floor":"11","rooms":"5","bedrooms":"3","conference_room":null,"suites":null,"wc":"3","bathroom":null,"shower":null,"fireplace":null,"air_conditioner":null,"balcony":null,"veranda":"34","loft":null,"bodrum":"3","mansard":null,"parking":null,"garage":null,"dist_from_tbilisi":null,"dist_from_cent_street":null,"box":null,"buildings":null,"administration_building":null,"workroom":null,"stockroom":null,"coefficient_k1":null,"coefficient_k2":null}}