{"posting_id":"10013709","locale":"ka","type":"იყიდება","property_type":"საკუთარი სახლი","date":"2015-08-11","additional_info":"სათავსო, ინტერნეტი, ტელეფონი, გათბობა: ცენტრალური, გაზი, დენი, ცხ წყალი: გაზი, დენი \n სასწრაფოდ...","details":{"daily_rent":null,"for_rent":"2500 $ / 5.43 $ m²","for_sale":"235000 $ / 510.87 $ m²","for_lease":null,"est_lease_price":null,"rent_price":"2500","rent_price_currency":"$","rent_price_sq_meter":"5.43","rent_price_dollars":2500.0,"rent_price_sq_meter_dollars":5.43,"rent_price_exchange_rate_to_dollars":1.0,"sale_price":"235000","sale_price_currency":"$","sale_price_sq_meter":"510.87","sale_price_dollars":235000.0,"sale_price_sq_meter_dollars":510.87,"sale_price_exchange_rate_to_dollars":1.0,"space":"460","space_measurement":"კვ.მ.","land":"1100","land_measurement":"კვ.მ.","renovation":"მიმდინარე რემონტი","view":"ლამაზი","project":null,"condition":"ახალი აშენებული","function":null,"address":"თბილისი, საბურთალო, დიღომი 1","address_city":"თბილისი","address_area":"საბურთალო","address_district":"დიღომი 1","address_street":null,"address_number":null,"phone":"2471020; 595925020;","cadastral":null},"specs":{"all_floors":"3","floor":null,"rooms":"12","bedrooms":"7","conference_room":null,"suites":null,"wc":"3","bathroom":"3","shower":"3","fireplace":null,"air_conditioner":null,"balcony":"4","veranda":null,"loft":null,"bodrum":null,"mansard":null,"parking":null,"garage":null,"dist_from_tbilisi":null,"dist_from_cent_street":null,"box":null,"buildings":null,"administration_building":null,"workroom":null,"stockroom":null,"coefficient_k1":null,"coefficient_k2":null}}