{"posting_id":"10046927","locale":"ka","type":"იყიდება","property_type":"მიწა","date":"2015-02-27","additional_info":"სახნავ-სათესი, სარწყავი, კომუნიკაციები: დენი, გაზი, წყალი \n ნაკვეთის თავზე გადის სარწყავი არხი.ნაკვეთთან ახლოს მიყვანილია კომუნიკაციები, შესაძლებელია სახლის აშენებაც, რეესტრში გატარებულია.","details":{"daily_rent":null,"for_rent":null,"for_sale":"7000 $ / 2.00 $ m²","for_lease":null,"est_lease_price":null,"rent_price":null,"rent_price_currency":null,"rent_price_sq_meter":null,"rent_price_dollars":null,"rent_price_sq_meter_dollars":null,"rent_price_exchange_rate_to_dollars":null,"sale_price":"7000","sale_price_currency":"$","sale_price_sq_meter":"2.00","sale_price_dollars":7000.0,"sale_price_sq_meter_dollars":2.0,"sale_price_exchange_rate_to_dollars":1.0,"space":"3500","space_measurement":"კვ.მ.","land":null,"land_measurement":null,"renovation":null,"view":null,"project":null,"condition":null,"function":"სასოფლო","address":"მუხრანი","address_city":"მუხრანი","address_area":null,"address_district":null,"address_street":null,"address_number":null,"phone":"598007644; 597760669;","cadastral":null},"specs":{"all_floors":null,"floor":null,"rooms":null,"bedrooms":null,"conference_room":null,"suites":null,"wc":null,"bathroom":null,"shower":null,"fireplace":null,"air_conditioner":null,"balcony":null,"veranda":null,"loft":null,"bodrum":null,"mansard":null,"parking":null,"garage":null,"dist_from_tbilisi":"30","dist_from_cent_street":"0.8","box":null,"buildings":null,"administration_building":null,"workroom":null,"stockroom":null,"coefficient_k1":null,"coefficient_k2":null}}