{"posting_id":"6832604","locale":"ka","type":"ქირავდება","property_type":"საკუთარი სახლი","date":"2014-04-17","additional_info":"ავეჯი, ტექნიკა, ტელეფონი, გათბობა: გაზი, ცხ წყალი: გაზი \n შესაძლებელია გაქირავდეს მხოლოდ მეორე სართული 1000 $ 150კვ.მ","details":{"daily_rent":null,"for_rent":"2000 $ / 8.00 $ m²","for_sale":null,"for_lease":null,"rent_price":"2000","rent_price_currency":"$","rent_price_exchange_rate":1,"rent_price_sq_meter":"8.00","sale_price":null,"sale_price_currency":null,"sale_price_exchange_rate":1,"sale_price_sq_meter":null,"space":"250","space_measurement":"კვ.მ.","land":"500","land_measurement":"კვ.მ.","renovation":"ახალი გარემონტებული","view":null,"project":null,"condition":null,"function":null,"address":"თბილისი, ვაკე-საბურთალო, ვეძისი, ვაზისუბნის ქ.","address_city":"თბილისი","address_area":"ვაკე-საბურთალო","address_district":"ვეძისი","address_street":"ვაზისუბნის ქ.","address_number":null,"phone":"2471020; 595925010;","cadastral":null},"specs":{"all_floors":"2","floor":null,"rooms":"6","bedrooms":"2","conference_room":null,"wc":"2","bathroom":null,"shower":null,"fireplace":"1","air_conditioner":null,"balcony":null,"veranda":"25","loft":null,"bodrum":null,"mansard":null,"parking":null,"garage":"1","dist_from_tbilisi":null,"dist_from_cent_street":null,"box":null,"buildings":null,"administration_building":null,"workroom":null,"stockroom":null,"coefficient_k1":null,"coefficient_k2":null}}