{"posting_id":"10055343","locale":"ka","type":"იყიდება","property_type":"ბინა","date":"2015-07-17","additional_info":"დუპლექსი \n იყიდება აღმაშენებლის გამზირზე ('აპოლოს' პირდაპირ)დუპლექსის ტიპის ბინა 3-4 სართული, 60კვ.მ+70კვ.მ","details":{"daily_rent":null,"for_rent":"700 $ / 5.38 $ m²","for_sale":"90000 $ / 692.31 $ m²","for_lease":null,"est_lease_price":null,"rent_price":"700","rent_price_currency":"$","rent_price_sq_meter":"5.38","rent_price_dollars":700.0,"rent_price_sq_meter_dollars":5.38,"rent_price_exchange_rate_to_dollars":1.0,"sale_price":"90000","sale_price_currency":"$","sale_price_sq_meter":"692.31","sale_price_dollars":90000.0,"sale_price_sq_meter_dollars":692.31,"sale_price_exchange_rate_to_dollars":1.0,"space":"130","space_measurement":"კვ.მ.","land":null,"land_measurement":null,"renovation":"ძველი გარემონტებული","view":null,"project":"არასტანდარტული","condition":null,"function":null,"address":"თბილისი, ჩუღურეთი, ჩუღურეთი, აღმაშენებლის გამზ.","address_city":"თბილისი","address_area":"ჩუღურეთი","address_district":"ჩუღურეთი","address_street":"აღმაშენებლის გამზ.","address_number":null,"phone":"2471020; 595925030;","cadastral":null},"specs":{"all_floors":"4","floor":"3","rooms":"5","bedrooms":null,"conference_room":null,"suites":null,"wc":"2","bathroom":"1","shower":null,"fireplace":null,"air_conditioner":null,"balcony":"1","veranda":null,"loft":null,"bodrum":null,"mansard":null,"parking":null,"garage":null,"dist_from_tbilisi":null,"dist_from_cent_street":null,"box":null,"buildings":null,"administration_building":null,"workroom":null,"stockroom":null,"coefficient_k1":null,"coefficient_k2":null}}