{"posting_id":"8087139","locale":"en","type":"for rent","property_type":"office","date":"2014-07-09","additional_info":"Storeroom, Network, Alarm System, Generator, Heating system: gas, Hot water: gas","details":{"daily_rent":null,"for_rent":"1178 $ / 19 $ m²","for_sale":null,"for_lease":null,"est_lease_price":null,"rent_price":"1178","rent_price_currency":"$","rent_price_sq_meter":"19","rent_price_dollars":1178.0,"rent_price_sq_meter_dollars":19.0,"rent_price_exchange_rate_to_dollars":1.0,"sale_price":null,"sale_price_currency":null,"sale_price_sq_meter":null,"sale_price_dollars":null,"sale_price_sq_meter_dollars":null,"sale_price_exchange_rate_to_dollars":null,"space":"62","space_measurement":"sq.m.","land":null,"land_measurement":null,"renovation":"Eurodesigne","view":"Yeard","project":null,"condition":"New building","function":null,"address":"Tbilisi, Vake-Saburtalo,  Saburtalo, Aslanidi st.","address_city":"Tbilisi","address_area":"Vake-Saburtalo","address_district":"Saburtalo","address_street":"Aslanidi st.","address_number":null,"phone":"2471020; 595925020;","cadastral":null},"specs":{"all_floors":"4","floor":"1","rooms":"4","bedrooms":null,"conference_room":null,"suites":null,"wc":"3","bathroom":null,"shower":null,"fireplace":"1","air_conditioner":"4","balcony":"2","veranda":null,"loft":null,"bodrum":null,"mansard":null,"parking":"3","garage":null,"dist_from_tbilisi":null,"dist_from_cent_street":null,"box":null,"buildings":null,"administration_building":null,"workroom":null,"stockroom":null,"coefficient_k1":null,"coefficient_k2":null}}