{"posting_id":"10004219","locale":"ka","type":"იყიდება","property_type":"ბინა","date":"2014-04-22","additional_info":"აპარტამენტი , 1 საძინებელი, 1 სველი წერტილი, დიდი მისაღები ოთახი  ამერიკული სამზარეულო და ფართო ტერასა ზღვის ხედით.\r\nRef.: 1103S","details":{"daily_rent":null,"for_rent":null,"for_sale":"68000 € / 1133.33 € m²","for_lease":null,"est_lease_price":null,"rent_price":null,"rent_price_currency":null,"rent_price_sq_meter":null,"rent_price_dollars":null,"rent_price_sq_meter_dollars":null,"rent_price_exchange_rate_to_dollars":null,"sale_price":"68000","sale_price_currency":"€","sale_price_sq_meter":"1133.33","sale_price_dollars":93840.0,"sale_price_sq_meter_dollars":1563.9953999999998,"sale_price_exchange_rate_to_dollars":1.38,"space":"60","space_measurement":"კვ.მ.","land":null,"land_measurement":null,"renovation":null,"view":null,"project":null,"condition":null,"function":null,"address":"ესპანეთი, ალიკანტე, არენალეს დელ სოლ","address_city":"ესპანეთი","address_area":"ალიკანტე","address_district":"არენალეს დელ სოლ","address_street":null,"address_number":null,"phone":"2471020; 595925020;","cadastral":null},"specs":{"all_floors":"1","floor":"1","rooms":"1","bedrooms":"1","conference_room":null,"suites":null,"wc":"1","bathroom":null,"shower":null,"fireplace":null,"air_conditioner":null,"balcony":null,"veranda":null,"loft":null,"bodrum":null,"mansard":null,"parking":null,"garage":null,"dist_from_tbilisi":null,"dist_from_cent_street":null,"box":null,"buildings":null,"administration_building":null,"workroom":null,"stockroom":null,"coefficient_k1":null,"coefficient_k2":null}}